exampleData/__init__.py
exampleData/getdata.py
exampleData-9.0.dist-info/METADATA
exampleData-9.0.dist-info/WHEEL
exampleData-9.0.dist-info/top_level.txt
exampleData-9.0.dist-info/RECORD
