Metadata-Version: 2.1
Name: exampleData
Version: 9.0
Summary: Package for example data for numerical study
Home-page: https://github.com/NCQH/exampleData
Author: NCQH
Author-email: ncquochuy21@gmail.com
Classifier: Programming Language :: Python :: 3
Requires-Dist: numpy
Requires-Dist: requests
